playwright_request/__init__.py
playwright_request/_builder.py
playwright_request/async_builder.py
playwright_request/sync_builder.py
playwright_apirequest_builder-1.0.0.dist-info/LICENSE
playwright_apirequest_builder-1.0.0.dist-info/METADATA
playwright_apirequest_builder-1.0.0.dist-info/WHEEL
playwright_apirequest_builder-1.0.0.dist-info/top_level.txt
playwright_apirequest_builder-1.0.0.dist-info/RECORD
