Metadata-Version: 2.1
Name: playwright-apirequest-builder
Version: 1.0.0
Summary: Playwright APIRequest builder
Home-page: https://github.com/w13b3/playwright-apirequest-builder
Author: Wiebe
Author-email: wiebe@email.com
License: Mozilla Public License Version 2.0
Classifier: Development Status :: 5 - Production/Stable
Classifier: License :: OSI Approved :: Mozilla Public License 2.0 (MPL 2.0)
Classifier: Operating System :: OS Independent
Classifier: Programming Language :: Python
Classifier: Programming Language :: Python :: 3
Classifier: Programming Language :: Python :: 3.8
Classifier: Programming Language :: Python :: 3.9
Classifier: Programming Language :: Python :: 3.10
Classifier: Programming Language :: Python :: 3.11
Classifier: Programming Language :: Python :: 3.12
Classifier: Programming Language :: Python :: 3 :: Only
Classifier: Typing :: Typed
Classifier: Intended Audience :: Developers
Classifier: Topic :: Software Development
Classifier: Topic :: Software Development :: Build Tools
Classifier: Topic :: Software Development :: Libraries :: Python Modules
Requires-Python: >=3.8.0, <4
License-File: LICENSE
Requires-Dist: playwright (>=1.26.0)
